supervisor/__init__.py
supervisor/childutils.py
supervisor/compat.py
supervisor/confecho.py
supervisor/datatypes.py
supervisor/dispatchers.py
supervisor/events.py
supervisor/http.py
supervisor/http_client.py
supervisor/loggers.py
supervisor/options.py
supervisor/pidproxy.py
supervisor/poller.py
supervisor/process.py
supervisor/rpcinterface.py
supervisor/socket_manager.py
supervisor/states.py
supervisor/supervisorctl.py
supervisor/supervisord.py
supervisor/templating.py
supervisor/version.txt
supervisor/web.py
supervisor/xmlrpc.py
supervisor/__pycache__/__init__.cpython-38.pyc
supervisor/__pycache__/childutils.cpython-38.pyc
supervisor/__pycache__/compat.cpython-38.pyc
supervisor/__pycache__/confecho.cpython-38.pyc
supervisor/__pycache__/datatypes.cpython-38.pyc
supervisor/__pycache__/dispatchers.cpython-38.pyc
supervisor/__pycache__/events.cpython-38.pyc
supervisor/__pycache__/http.cpython-38.pyc
supervisor/__pycache__/http_client.cpython-38.pyc
supervisor/__pycache__/loggers.cpython-38.pyc
supervisor/__pycache__/options.cpython-38.pyc
supervisor/__pycache__/pidproxy.cpython-38.pyc
supervisor/__pycache__/poller.cpython-38.pyc
supervisor/__pycache__/process.cpython-38.pyc
supervisor/__pycache__/rpcinterface.cpython-38.pyc
supervisor/__pycache__/socket_manager.cpython-38.pyc
supervisor/__pycache__/states.cpython-38.pyc
supervisor/__pycache__/supervisorctl.cpython-38.pyc
supervisor/__pycache__/supervisord.cpython-38.pyc
supervisor/__pycache__/templating.cpython-38.pyc
supervisor/__pycache__/web.cpython-38.pyc
supervisor/__pycache__/xmlrpc.cpython-38.pyc
supervisor/medusa/__init__.py
supervisor/medusa/asynchat_25.py
supervisor/medusa/asyncore_25.py
supervisor/medusa/auth_handler.py
supervisor/medusa/counter.py
supervisor/medusa/default_handler.py
supervisor/medusa/filesys.py
supervisor/medusa/http_date.py
supervisor/medusa/http_server.py
supervisor/medusa/logger.py
supervisor/medusa/m_syslog.py
supervisor/medusa/medusa_gif.py
supervisor/medusa/producers.py
supervisor-4.2.4.dist-info/LICENSES.txt
supervisor-4.2.4.dist-info/METADATA
supervisor-4.2.4.dist-info/WHEEL
supervisor-4.2.4.dist-info/entry_points.txt
supervisor-4.2.4.dist-info/top_level.txt
supervisor-4.2.4.dist-info/RECORD
